{
  "questions": [
    {
      "question": "O que é front-end?",
      "options": ["Parte de um Sistema que é oculta ao usuário", "Parte de um sistema é visível e interativa ao usuário", "Uma instância em um servidor cloud","A infraestrtura de um site"],
      "correctAnswer": "Parte de um sistema é visível e interativa ao usuário"
    },
    {
      "question": "O que é ReactJS?",
      "options": ["Uma poderosa biblioteca do JS", "Uma linguagem de programação", "Um servidor cloud', 'Uma ferramenta do Vscode"],
      "correctAnswer": "Uma poderosa biblioteca do JS"
    },
    {
      "question": "Quais as principais tecnologias do mundo front-end?",
      "options": "['Javascript, Golang e Python', 'AWS, GCP, Azure', 'Kotlin, HTML e CSS', 'HTML, CSS, JavaScript']",
      "correctAnswer": "HTML, CSS, JavaScript"
    },
    {
      "question": "Em que ano o ReactJS foi lançado?",
      "options":["2010", "2012", "2013", "2015"],
      "correctAnswer":"2013"
    },
    {
      "question": "O que são hooks no React?",
      "options":["São funcões de chamar arquivos", "Um componente","Funções que permitem a você ligar-se aos recursos de state e ciclo de vida do React a partir de componentes funcionais"],
      "correctAnswer":"Funções que permitem a você ligar-se aos recursos de state e ciclo de vida do React a partir de componentes funcionais."
    }
    
  ]
}